oeispy
