Metadata-Version: 2.1
Name: oeispy
Version: 0.0.5
Summary: Simple Python Library for OEIS
Home-page: https://github.com/phantom-5/oeispy
Author: Rudra M Biswal
Author-email: rickrudra@gmail.com
License: MIT
Keywords: oeis
Platform: UNKNOWN
Classifier: Development Status :: 4 - Beta
Classifier: Intended Audience :: Education
Classifier: Operating System :: Microsoft :: Windows :: Windows 10
Classifier: License :: OSI Approved :: MIT License
Classifier: Programming Language :: Python :: 3
